dftds/__init__.py
dftds/kvalue_repository.py
dftds/kvalue_repository_flash.py
dftds/tds.py
micropython_dftds-0.0.1.dist-info/METADATA
micropython_dftds-0.0.1.dist-info/WHEEL
micropython_dftds-0.0.1.dist-info/top_level.txt
micropython_dftds-0.0.1.dist-info/RECORD
