Metadata-Version: 2.1
Name: micropython-dftds
Version: 0.0.1
Summary: MicroPython library for the TDS meter sensor
Home-page: https://github.com/WendelHime/micropython-dftds
Author: Wendel Hime Lino Castro
Author-email: wendelhime@hotmail.com
License: MIT
Project-URL: github, https://github.com/WendelHime/micropython-dftds
Keywords: micropython,electronics
Classifier: Development Status :: 1 - Planning
Classifier: Intended Audience :: Developers
Classifier: Programming Language :: Python :: Implementation :: MicroPython
